largest_face_detector/__init__.py
largest_face_detector/face_detector.py
test/__init__.py
test/test_face_detector.py
test/test_image.jpeg
test/resources/test_image.jpeg
largest_frontal_face_detector-1.0.0.dist-info/LICENSE.txt
largest_frontal_face_detector-1.0.0.dist-info/METADATA
largest_frontal_face_detector-1.0.0.dist-info/WHEEL
largest_frontal_face_detector-1.0.0.dist-info/top_level.txt
largest_frontal_face_detector-1.0.0.dist-info/RECORD
