Metadata-Version: 2.1
Name: largest-frontal-face-detector
Version: 1.0.0
Summary: Python pakage for detecting largest face in an image
Home-page: https://github.com/devangkulshreshtha/largest_face_detector
Author: Devang Kulshreshtha
Author-email: devang.kulshreshtha.cse14@itbhu.ac.in
License: UNKNOWN
Platform: UNKNOWN
Classifier: Programming Language :: Python :: 3
Classifier: License :: OSI Approved :: MIT License
Classifier: Operating System :: OS Independent
Requires-Python: >=3.6
Requires-Dist: numpy
Requires-Dist: dlib
Requires-Dist: pillow
